BMI_YCB/BMI.py
BMI_YCB-0.0.0.1.dist-info/METADATA
BMI_YCB-0.0.0.1.dist-info/WHEEL
BMI_YCB-0.0.0.1.dist-info/top_level.txt
BMI_YCB-0.0.0.1.dist-info/RECORD
