Metadata-Version: 2.1
Name: BMI-YCB
Version: 0.0.0.1
Summary: My BMI Package
Home-page: https://bayech.notion.site/cc0cd80cb4844a16b28d3986a92b2c1a?v=ac1a0656508c4a8e9bdecca967f4e1f3
Author: YeonCheol Bae
Author-email: ycbae123@gmail.com
License: MIT
Platform: UNKNOWN
Requires-Python: >=3
